sot/__init__.py
sot/cqt.py
sot/features.py
sot/losses.py
sot_loss-0.1.3.dist-info/licenses/LICENSE
sot_loss-0.1.3.dist-info/METADATA
sot_loss-0.1.3.dist-info/WHEEL
sot_loss-0.1.3.dist-info/top_level.txt
sot_loss-0.1.3.dist-info/RECORD
