Metadata-Version: 2.4
Name: sot-loss
Version: 0.1.3
Summary: A PyTorch implementation of Spectral Optimal Transport (SOT) losses for audio.
Author: Bernardo Torres
License: MIT License
Project-URL: Homepage, https://github.com/bernardo-torres/spectral-optimal-transport
Project-URL: Bug Tracker, https://github.com/bernardo-torres/spectral-optimal-transport/issues
Classifier: Programming Language :: Python :: 3
Classifier: License :: OSI Approved :: MIT License
Classifier: Operating System :: OS Independent
Classifier: Intended Audience :: Science/Research
Classifier: Topic :: Scientific/Engineering :: Artificial Intelligence
Requires-Python: >=3.9
License-File: LICENSE
Requires-Dist: torch>=2.0.1
Requires-Dist: torchaudio>=2.0.0
Requires-Dist: numpy>=1.20.0
Requires-Dist: scipy>=1.8.0
Dynamic: license-file
